zodbcode
